osc_github_devops-0.1.44.dist-info/METADATA
osc_github_devops-0.1.44.dist-info/WHEEL
osc_github_devops-0.1.44.dist-info/entry_points.txt
osc_github_devops-0.1.44.dist-info/licenses/LICENSES/Apache-2.0.txt
osc_github_devops/__init__.py
osc_github_devops/cli.py
osc_github_devops/test.sh
osc_github_devops-0.1.44.dist-info/RECORD
