Metadata-Version: 2.4
Name: osc-github-devops
Version: 0.1.44
Summary: Template Python project
Keywords: GitHub
Author-Email: Matthew Watkins <93649628+ModeSevenIndustrialSolutions@users.noreply.github.com>
License-Expression: Apache-2.0
License-File: LICENSES/Apache-2.0.txt
Classifier: Intended Audience :: Developers
Classifier: Intended Audience :: Science/Research
Classifier: Operating System :: MacOS
Classifier: Operating System :: Microsoft :: Windows
Classifier: Operating System :: Unix
Classifier: Programming Language :: Python
Classifier: Programming Language :: Python :: 3
Classifier: Programming Language :: Python :: 3 :: Only
Classifier: Programming Language :: Python :: 3.14
Classifier: Programming Language :: Python :: 3.13
Classifier: Programming Language :: Python :: 3.12
Classifier: Programming Language :: Python :: 3.11
Classifier: Topic :: Office/Business :: Financial
Classifier: Topic :: Scientific/Engineering
Classifier: Topic :: Software Development
Project-URL: Homepage, https://github.com/os-climate/osc-github-devops
Project-URL: Repository, https://github.com/os-climate/osc-github-devops
Project-URL: Downloads, https://github.com/os-climate/osc-github-devops/releases
Project-URL: Bug Tracker, https://github.com/os-climate/osc-github-devops/issues
Project-URL: Documentation, https://github.com/os-climate/osc-github-devops/tree/main/docs
Project-URL: Source Code, https://github.com/os-climate/osc-github-devops
Requires-Python: >=3.11
Requires-Dist: typer>=0.15.2
Requires-Dist: jupyterlab>=4.3.6
